py_stateful_map.py
py_stateful_map-0.3.dist-info/LICENSE
py_stateful_map-0.3.dist-info/METADATA
py_stateful_map-0.3.dist-info/WHEEL
py_stateful_map-0.3.dist-info/top_level.txt
py_stateful_map-0.3.dist-info/RECORD
