Metadata-Version: 2.1
Name: py_stateful_map
Version: 0.3
Summary: A an extension of the multiproc/thread map that supports stateful workers & size-aware iterators.
Author: Leonid Boytsov
Author-email: leo@boytsov.info
License: Apache 2.0
Requires-Python: >=3.6
License-File: LICENSE
